pypexel/__init__.py
pypexel/async_api/__init__.py
pypexel/async_api/async_api.py
pypexel/async_api/async_api_base.py
pypexel/async_api/async_api_collections.py
pypexel/async_api/async_api_photos.py
pypexel/async_api/async_api_videos.py
pypexel/models/__init__.py
pypexel/models/models_collection.py
pypexel/models/models_photo.py
pypexel/models/models_video.py
pypexel-0.0.2.dist-info/METADATA
pypexel-0.0.2.dist-info/WHEEL
pypexel-0.0.2.dist-info/top_level.txt
pypexel-0.0.2.dist-info/RECORD
