Metadata-Version: 2.4
Name: pypexel
Version: 0.0.2
Summary: Async Object-oriented Python SDK for the Pexels API.
Author-email: iwatkot <iwatkot@gmail.com>
License: MIT License
Project-URL: Homepage, https://github.com/iwatkot/pypexel
Project-URL: Repository, https://github.com/iwatkot/pypexel
Keywords: pexels,sdk,async,images,videos
Classifier: Programming Language :: Python :: 3.11
Classifier: Programming Language :: Python :: 3.12
Classifier: License :: OSI Approved :: MIT License
Classifier: Operating System :: OS Independent
Requires-Dist: pydantic>=2.0.0
Requires-Dist: httpx>=0.20.0
